<?xml version="1.0" encoding="UTF-8"?>
<System>

	<!-- General config options -->
	<Configuration>	
		<Learning allowed = "true" creationOfNewContext = "true" loadPresetContext = "false"></Learning>	
	</Configuration>
	
	
	<StartingAgents>
	
		<Sensor Name="1" Source="1" Enum="true"></Sensor>
		<Sensor Name="2" Source="2" Enum="true"></Sensor>
		<Sensor Name="3" Source="3" Enum="true"></Sensor>
		<Sensor Name="4" Source="4" Enum="true"></Sensor>
		<Sensor Name="5" Source="5" Enum="true"></Sensor>
		<Sensor Name="6" Source="6" Enum="true"></Sensor>
		<Sensor Name="7" Source="7" Enum="true"></Sensor>
		<Sensor Name="8" Source="8" Enum="true"></Sensor>
		<Sensor Name="9" Source="9" Enum="true"></Sensor>
		<Sensor Name="10" Source="10" Enum="true"></Sensor>
		<Sensor Name="11" Source="11" Enum="true"></Sensor>
		<Sensor Name="12" Source="12" Enum="true"></Sensor>
		<Sensor Name="13" Source="13" Enum="true"></Sensor>
		<Sensor Name="14" Source="14" Enum="true"></Sensor>
		<Sensor Name="15" Source="15" Enum="true"></Sensor>
		<Sensor Name="16" Source="16" Enum="true"></Sensor>
		<Sensor Name="17" Source="17" Enum="true"></Sensor>
		<Sensor Name="18" Source="18" Enum="true"></Sensor>
		<Sensor Name="19" Source="19" Enum="true"></Sensor>
		<Sensor Name="20" Source="20" Enum="true"></Sensor>
		<Sensor Name="21" Source="21" Enum="true"></Sensor>
		<Sensor Name="22" Source="22" Enum="true"></Sensor>
		<Sensor Name="23" Source="23" Enum="true"></Sensor>
		<Sensor Name="24" Source="24" Enum="true"></Sensor>
		<Sensor Name="25" Source="25" Enum="true"></Sensor>
		<Sensor Name="26" Source="26" Enum="true"></Sensor>
		<Sensor Name="27" Source="27" Enum="true"></Sensor>
		<Sensor Name="28" Source="28" Enum="true"></Sensor>
		<Sensor Name="29" Source="29" Enum="true"></Sensor>
		<Sensor Name="30" Source="30" Enum="true"></Sensor>
		<Sensor Name="31" Source="31" Enum="true"></Sensor>
		<Sensor Name="32" Source="32" Enum="true"></Sensor>
		<Sensor Name="33" Source="33" Enum="true"></Sensor>
		<Sensor Name="34" Source="34" Enum="true"></Sensor>
		<Sensor Name="35" Source="35" Enum="true"></Sensor>
		<Sensor Name="36" Source="36" Enum="true"></Sensor>
		<Sensor Name="37" Source="37" Enum="true"></Sensor>
		<Sensor Name="38" Source="38" Enum="true"></Sensor>
		<Sensor Name="39" Source="39" Enum="true"></Sensor>
		<Sensor Name="40" Source="40" Enum="true"></Sensor>
		<Sensor Name="41" Source="41" Enum="true"></Sensor>
		<Sensor Name="42" Source="42" Enum="true"></Sensor>
		<Sensor Name="43" Source="43" Enum="true"></Sensor>
		<Sensor Name="44" Source="44" Enum="true"></Sensor>
		<Sensor Name="45" Source="45" Enum="true"></Sensor>
		<Sensor Name="46" Source="46" Enum="true"></Sensor>
		<Sensor Name="47" Source="47" Enum="true"></Sensor>
		<Sensor Name="48" Source="48" Enum="true"></Sensor>
		<Sensor Name="49" Source="49" Enum="true"></Sensor>
		<Sensor Name="50" Source="50" Enum="true"></Sensor>
		<Sensor Name="51" Source="51" Enum="true"></Sensor>
		<Sensor Name="52" Source="52" Enum="true"></Sensor>
		<Sensor Name="53" Source="53" Enum="true"></Sensor>
		<Sensor Name="54" Source="54" Enum="true"></Sensor>
		<Sensor Name="55" Source="55" Enum="true"></Sensor>
		<Sensor Name="56" Source="56" Enum="true"></Sensor>
		<Sensor Name="57" Source="57" Enum="true"></Sensor>
		<Sensor Name="58" Source="58" Enum="true"></Sensor>
		<Sensor Name="59" Source="59" Enum="true"></Sensor>
		<Sensor Name="60" Source="60" Enum="true"></Sensor>
		<Sensor Name="61" Source="61" Enum="true"></Sensor>
		<Sensor Name="62" Source="62" Enum="true"></Sensor>
		<Sensor Name="63" Source="63" Enum="true"></Sensor>
		<Sensor Name="64" Source="64" Enum="true"></Sensor>
		<Sensor Name="65" Source="65" Enum="true"></Sensor>
		<Sensor Name="66" Source="66" Enum="true"></Sensor>
		<Sensor Name="67" Source="67" Enum="true"></Sensor>
		<Sensor Name="68" Source="68" Enum="true"></Sensor>
		<Sensor Name="69" Source="69" Enum="true"></Sensor>
		<Sensor Name="70" Source="70" Enum="true"></Sensor>
		<Sensor Name="71" Source="71" Enum="true"></Sensor>
		<Sensor Name="72" Source="72" Enum="true"></Sensor>
		<Sensor Name="73" Source="73" Enum="true"></Sensor>
		<Sensor Name="74" Source="74" Enum="true"></Sensor>
		<Sensor Name="75" Source="75" Enum="true"></Sensor>
		<Sensor Name="76" Source="76" Enum="true"></Sensor>
		<Sensor Name="77" Source="77" Enum="true"></Sensor>
		<Sensor Name="78" Source="78" Enum="true"></Sensor>
		<Sensor Name="79" Source="79" Enum="true"></Sensor>
		<Sensor Name="80" Source="80" Enum="true"></Sensor>
		<Sensor Name="81" Source="81" Enum="true"></Sensor>
		<Sensor Name="82" Source="82" Enum="true"></Sensor>
		<Sensor Name="83" Source="83" Enum="true"></Sensor>
		<Sensor Name="84" Source="84" Enum="true"></Sensor>
		<Sensor Name="85" Source="85" Enum="true"></Sensor>
		<Sensor Name="86" Source="86" Enum="true"></Sensor>
		<Sensor Name="87" Source="87" Enum="true"></Sensor>
		<Sensor Name="88" Source="88" Enum="true"></Sensor>
		<Sensor Name="89" Source="89" Enum="true"></Sensor>
		<Sensor Name="90" Source="90" Enum="true"></Sensor>
		<Sensor Name="91" Source="91" Enum="true"></Sensor>
		<Sensor Name="92" Source="92" Enum="true"></Sensor>
		<Sensor Name="93" Source="93" Enum="true"></Sensor>
		<Sensor Name="94" Source="94" Enum="true"></Sensor>
		<Sensor Name="95" Source="95" Enum="true"></Sensor>
		<Sensor Name="96" Source="96" Enum="true"></Sensor>
		<Sensor Name="97" Source="97" Enum="true"></Sensor>
		<Sensor Name="98" Source="98" Enum="true"></Sensor>
		<Sensor Name="99" Source="99" Enum="true"></Sensor>
		<Sensor Name="100" Source="100" Enum="true"></Sensor>
		<Sensor Name="101" Source="101" Enum="true"></Sensor>
		<Sensor Name="102" Source="102" Enum="true"></Sensor>
		<Sensor Name="103" Source="103" Enum="true"></Sensor>
		<Sensor Name="104" Source="104" Enum="true"></Sensor>
		<Sensor Name="105" Source="105" Enum="true"></Sensor>
		<Sensor Name="106" Source="106" Enum="true"></Sensor>
		<Sensor Name="107" Source="107" Enum="true"></Sensor>
		<Sensor Name="108" Source="108" Enum="true"></Sensor>
		<Sensor Name="109" Source="109" Enum="true"></Sensor>
		<Sensor Name="110" Source="110" Enum="true"></Sensor>
		<Sensor Name="111" Source="111" Enum="true"></Sensor>
		<Sensor Name="112" Source="112" Enum="true"></Sensor>
		<Sensor Name="113" Source="113" Enum="true"></Sensor>
		<Sensor Name="114" Source="114" Enum="true"></Sensor>
		<Sensor Name="115" Source="115" Enum="true"></Sensor>
		<Sensor Name="116" Source="116" Enum="true"></Sensor>
		<Sensor Name="117" Source="117" Enum="true"></Sensor>
		<Sensor Name="118" Source="118" Enum="true"></Sensor>
		<Sensor Name="119" Source="119" Enum="true"></Sensor>
		<Sensor Name="120" Source="120" Enum="true"></Sensor>
		<Sensor Name="121" Source="121" Enum="true"></Sensor>
		<Sensor Name="122" Source="122" Enum="true"></Sensor>
		<Sensor Name="123" Source="123" Enum="true"></Sensor>
		<Sensor Name="124" Source="124" Enum="true"></Sensor>
		<Sensor Name="125" Source="125" Enum="true"></Sensor>
		<Sensor Name="126" Source="126" Enum="true"></Sensor>
		<Sensor Name="127" Source="127" Enum="true"></Sensor>
		<Sensor Name="128" Source="128" Enum="true"></Sensor>
		<Sensor Name="129" Source="129" Enum="true"></Sensor>
		<Sensor Name="130" Source="130" Enum="true"></Sensor>
		<Sensor Name="131" Source="131" Enum="true"></Sensor>
		<Sensor Name="132" Source="132" Enum="true"></Sensor>
		<Sensor Name="133" Source="133" Enum="true"></Sensor>
		<Sensor Name="134" Source="134" Enum="true"></Sensor>
		<Sensor Name="135" Source="135" Enum="true"></Sensor>
		<Sensor Name="136" Source="136" Enum="true"></Sensor>
		<Sensor Name="137" Source="137" Enum="true"></Sensor>
		<Sensor Name="138" Source="138" Enum="true"></Sensor>
		<Sensor Name="139" Source="139" Enum="true"></Sensor>
		<Sensor Name="140" Source="140" Enum="true"></Sensor>
		<Sensor Name="141" Source="141" Enum="true"></Sensor>
		<Sensor Name="142" Source="142" Enum="true"></Sensor>
		<Sensor Name="143" Source="143" Enum="true"></Sensor>
		<Sensor Name="144" Source="144" Enum="true"></Sensor>
		<Sensor Name="145" Source="145" Enum="true"></Sensor>
		<Sensor Name="146" Source="146" Enum="true"></Sensor>
		<Sensor Name="147" Source="147" Enum="true"></Sensor>
		<Sensor Name="148" Source="148" Enum="true"></Sensor>
		<Sensor Name="149" Source="149" Enum="true"></Sensor>
		<Sensor Name="150" Source="150" Enum="true"></Sensor>
		<Sensor Name="151" Source="151" Enum="true"></Sensor>
		<Sensor Name="152" Source="152" Enum="true"></Sensor>
		<Sensor Name="153" Source="153" Enum="true"></Sensor>
		<Sensor Name="154" Source="154" Enum="true"></Sensor>
		<Sensor Name="155" Source="155" Enum="true"></Sensor>
		<Sensor Name="156" Source="156" Enum="true"></Sensor>
		<Sensor Name="157" Source="157" Enum="true"></Sensor>
		<Sensor Name="158" Source="158" Enum="true"></Sensor>
		<Sensor Name="159" Source="159" Enum="true"></Sensor>
		<Sensor Name="160" Source="160" Enum="true"></Sensor>
		<Sensor Name="161" Source="161" Enum="true"></Sensor>
		<Sensor Name="162" Source="162" Enum="true"></Sensor>
		<Sensor Name="163" Source="163" Enum="true"></Sensor>
		<Sensor Name="164" Source="164" Enum="true"></Sensor>
		<Sensor Name="165" Source="165" Enum="true"></Sensor>
		<Sensor Name="166" Source="166" Enum="true"></Sensor>
		<Sensor Name="167" Source="167" Enum="true"></Sensor>
		<Sensor Name="168" Source="168" Enum="true"></Sensor>
		<Sensor Name="169" Source="169" Enum="true"></Sensor>
		<Sensor Name="170" Source="170" Enum="true"></Sensor>
		<Sensor Name="171" Source="171" Enum="true"></Sensor>
		<Sensor Name="172" Source="172" Enum="true"></Sensor>
		<Sensor Name="173" Source="173" Enum="true"></Sensor>
		<Sensor Name="174" Source="174" Enum="true"></Sensor>
		<Sensor Name="175" Source="175" Enum="true"></Sensor>
		<Sensor Name="176" Source="176" Enum="true"></Sensor>
		<Sensor Name="177" Source="177" Enum="true"></Sensor>
		<Sensor Name="178" Source="178" Enum="true"></Sensor>
		<Sensor Name="179" Source="179" Enum="true"></Sensor>
		<Sensor Name="180" Source="180" Enum="true"></Sensor>
		<Sensor Name="181" Source="181" Enum="true"></Sensor>
		<Sensor Name="182" Source="182" Enum="true"></Sensor>
		<Sensor Name="183" Source="183" Enum="true"></Sensor>
		<Sensor Name="184" Source="184" Enum="true"></Sensor>
		<Sensor Name="185" Source="185" Enum="true"></Sensor>
		<Sensor Name="186" Source="186" Enum="true"></Sensor>
		<Sensor Name="187" Source="187" Enum="true"></Sensor>
		<Sensor Name="188" Source="188" Enum="true"></Sensor>
		<Sensor Name="189" Source="189" Enum="true"></Sensor>
		<Sensor Name="190" Source="190" Enum="true"></Sensor>
		<Sensor Name="191" Source="191" Enum="true"></Sensor>
		<Sensor Name="192" Source="192" Enum="true"></Sensor>
		<Sensor Name="193" Source="193" Enum="true"></Sensor>
		<Sensor Name="194" Source="194" Enum="true"></Sensor>
		<Sensor Name="195" Source="195" Enum="true"></Sensor>
		<Sensor Name="196" Source="196" Enum="true"></Sensor>
		<Sensor Name="197" Source="197" Enum="true"></Sensor>
		<Sensor Name="198" Source="198" Enum="true"></Sensor>
		<Sensor Name="199" Source="199" Enum="true"></Sensor>
		<Sensor Name="200" Source="200" Enum="true"></Sensor>
		<Sensor Name="201" Source="201" Enum="true"></Sensor>
		<Sensor Name="202" Source="202" Enum="true"></Sensor>
		<Sensor Name="203" Source="203" Enum="true"></Sensor>
		<Sensor Name="204" Source="204" Enum="true"></Sensor>
		<Sensor Name="205" Source="205" Enum="true"></Sensor>
		<Sensor Name="206" Source="206" Enum="true"></Sensor>
		<Sensor Name="207" Source="207" Enum="true"></Sensor>
		<Sensor Name="208" Source="208" Enum="true"></Sensor>
		<Sensor Name="209" Source="209" Enum="true"></Sensor>
		<Sensor Name="210" Source="210" Enum="true"></Sensor>
		<Sensor Name="211" Source="211" Enum="true"></Sensor>
		<Sensor Name="212" Source="212" Enum="true"></Sensor>
		<Sensor Name="213" Source="213" Enum="true"></Sensor>
		<Sensor Name="214" Source="214" Enum="true"></Sensor>
		<Sensor Name="215" Source="215" Enum="true"></Sensor>
		<Sensor Name="216" Source="216" Enum="true"></Sensor>
		<Sensor Name="217" Source="217" Enum="true"></Sensor>
		<Sensor Name="218" Source="218" Enum="true"></Sensor>
		<Sensor Name="219" Source="219" Enum="true"></Sensor>
		<Sensor Name="220" Source="220" Enum="true"></Sensor>
		<Sensor Name="221" Source="221" Enum="true"></Sensor>
		<Sensor Name="222" Source="222" Enum="true"></Sensor>
		<Sensor Name="223" Source="223" Enum="true"></Sensor>
		<Sensor Name="224" Source="224" Enum="true"></Sensor>
		<Sensor Name="225" Source="225" Enum="true"></Sensor>
		<Sensor Name="226" Source="226" Enum="true"></Sensor>
		<Sensor Name="227" Source="227" Enum="true"></Sensor>
		<Sensor Name="228" Source="228" Enum="true"></Sensor>
		<Sensor Name="229" Source="229" Enum="true"></Sensor>
		<Sensor Name="230" Source="230" Enum="true"></Sensor>
		<Sensor Name="231" Source="231" Enum="true"></Sensor>
		<Sensor Name="232" Source="232" Enum="true"></Sensor>
		<Sensor Name="233" Source="233" Enum="true"></Sensor>
		<Sensor Name="234" Source="234" Enum="true"></Sensor>
		<Sensor Name="235" Source="235" Enum="true"></Sensor>
		<Sensor Name="236" Source="236" Enum="true"></Sensor>
		<Sensor Name="237" Source="237" Enum="true"></Sensor>
		<Sensor Name="238" Source="238" Enum="true"></Sensor>
		<Sensor Name="239" Source="239" Enum="true"></Sensor>
		<Sensor Name="240" Source="240" Enum="true"></Sensor>
		<Sensor Name="241" Source="241" Enum="true"></Sensor>
		<Sensor Name="242" Source="242" Enum="true"></Sensor>
		<Sensor Name="243" Source="243" Enum="true"></Sensor>
		<Sensor Name="244" Source="244" Enum="true"></Sensor>
		<Sensor Name="245" Source="245" Enum="true"></Sensor>
		<Sensor Name="246" Source="246" Enum="true"></Sensor>
		<Sensor Name="247" Source="247" Enum="true"></Sensor>
		<Sensor Name="248" Source="248" Enum="true"></Sensor>
		<Sensor Name="249" Source="249" Enum="true"></Sensor>
		<Sensor Name="250" Source="250" Enum="true"></Sensor>
		<Sensor Name="251" Source="251" Enum="true"></Sensor>
		<Sensor Name="252" Source="252" Enum="true"></Sensor>
		<Sensor Name="253" Source="253" Enum="true"></Sensor>
		<Sensor Name="254" Source="254" Enum="true"></Sensor>
		<Sensor Name="255" Source="255" Enum="true"></Sensor>
		<Sensor Name="256" Source="256" Enum="true"></Sensor>
		<Sensor Name="257" Source="257" Enum="true"></Sensor>
		<Sensor Name="258" Source="258" Enum="true"></Sensor>
		<Sensor Name="259" Source="259" Enum="true"></Sensor>
		<Sensor Name="260" Source="260" Enum="true"></Sensor>
		<Sensor Name="261" Source="261" Enum="true"></Sensor>
		<Sensor Name="262" Source="262" Enum="true"></Sensor>
		<Sensor Name="263" Source="263" Enum="true"></Sensor>
		<Sensor Name="264" Source="264" Enum="true"></Sensor>
		<Sensor Name="265" Source="265" Enum="true"></Sensor>
		<Sensor Name="266" Source="266" Enum="true"></Sensor>
		<Sensor Name="267" Source="267" Enum="true"></Sensor>
		<Sensor Name="268" Source="268" Enum="true"></Sensor>
		<Sensor Name="269" Source="269" Enum="true"></Sensor>
		<Sensor Name="270" Source="270" Enum="true"></Sensor>
		<Sensor Name="271" Source="271" Enum="true"></Sensor>
		<Sensor Name="272" Source="272" Enum="true"></Sensor>
		<Sensor Name="273" Source="273" Enum="true"></Sensor>
		<Sensor Name="274" Source="274" Enum="true"></Sensor>
		<Sensor Name="275" Source="275" Enum="true"></Sensor>
		<Sensor Name="276" Source="276" Enum="true"></Sensor>
		<Sensor Name="277" Source="277" Enum="true"></Sensor>
		<Sensor Name="278" Source="278" Enum="true"></Sensor>
		<Sensor Name="279" Source="279" Enum="true"></Sensor>
		<Sensor Name="280" Source="280" Enum="true"></Sensor>
		<Sensor Name="281" Source="281" Enum="true"></Sensor>
		<Sensor Name="282" Source="282" Enum="true"></Sensor>
		<Sensor Name="283" Source="283" Enum="true"></Sensor>
		<Sensor Name="284" Source="284" Enum="true"></Sensor>
		<Sensor Name="285" Source="285" Enum="true"></Sensor>
		<Sensor Name="286" Source="286" Enum="true"></Sensor>
		<Sensor Name="287" Source="287" Enum="true"></Sensor>
		<Sensor Name="288" Source="288" Enum="true"></Sensor>
		<Sensor Name="289" Source="289" Enum="true"></Sensor>
		<Sensor Name="290" Source="290" Enum="true"></Sensor>
		<Sensor Name="291" Source="291" Enum="true"></Sensor>
		<Sensor Name="292" Source="292" Enum="true"></Sensor>
		<Sensor Name="293" Source="293" Enum="true"></Sensor>
		<Sensor Name="294" Source="294" Enum="true"></Sensor>
		<Sensor Name="295" Source="295" Enum="true"></Sensor>
		<Sensor Name="296" Source="296" Enum="true"></Sensor>
		<Sensor Name="297" Source="297" Enum="true"></Sensor>
		<Sensor Name="298" Source="298" Enum="true"></Sensor>
		<Sensor Name="299" Source="299" Enum="true"></Sensor>
		<Sensor Name="300" Source="300" Enum="true"></Sensor>
		<Sensor Name="301" Source="301" Enum="true"></Sensor>
		<Sensor Name="302" Source="302" Enum="true"></Sensor>
		<Sensor Name="303" Source="303" Enum="true"></Sensor>
		<Sensor Name="304" Source="304" Enum="true"></Sensor>
		<Sensor Name="305" Source="305" Enum="true"></Sensor>
		<Sensor Name="306" Source="306" Enum="true"></Sensor>
		<Sensor Name="307" Source="307" Enum="true"></Sensor>
		<Sensor Name="308" Source="308" Enum="true"></Sensor>
		<Sensor Name="309" Source="309" Enum="true"></Sensor>
		<Sensor Name="310" Source="310" Enum="true"></Sensor>
		<Sensor Name="311" Source="311" Enum="true"></Sensor>
		<Sensor Name="312" Source="312" Enum="true"></Sensor>
		<Sensor Name="313" Source="313" Enum="true"></Sensor>
		<Sensor Name="314" Source="314" Enum="true"></Sensor>
		<Sensor Name="315" Source="315" Enum="true"></Sensor>
		<Sensor Name="316" Source="316" Enum="true"></Sensor>
		<Sensor Name="317" Source="317" Enum="true"></Sensor>
		<Sensor Name="318" Source="318" Enum="true"></Sensor>
		<Sensor Name="319" Source="319" Enum="true"></Sensor>
		<Sensor Name="320" Source="320" Enum="true"></Sensor>
		<Sensor Name="321" Source="321" Enum="true"></Sensor>
		<Sensor Name="322" Source="322" Enum="true"></Sensor>
		<Sensor Name="323" Source="323" Enum="true"></Sensor>
		<Sensor Name="324" Source="324" Enum="true"></Sensor>
		<Sensor Name="325" Source="325" Enum="true"></Sensor>
		<Sensor Name="326" Source="326" Enum="true"></Sensor>
		<Sensor Name="327" Source="327" Enum="true"></Sensor>
		<Sensor Name="328" Source="328" Enum="true"></Sensor>
		<Sensor Name="329" Source="329" Enum="true"></Sensor>
		<Sensor Name="330" Source="330" Enum="true"></Sensor>
		<Sensor Name="331" Source="331" Enum="true"></Sensor>
		<Sensor Name="332" Source="332" Enum="true"></Sensor>
		<Sensor Name="333" Source="333" Enum="true"></Sensor>
		<Sensor Name="334" Source="334" Enum="true"></Sensor>
		<Sensor Name="335" Source="335" Enum="true"></Sensor>
		<Sensor Name="336" Source="336" Enum="true"></Sensor>
		<Sensor Name="337" Source="337" Enum="true"></Sensor>
		<Sensor Name="338" Source="338" Enum="true"></Sensor>
		<Sensor Name="339" Source="339" Enum="true"></Sensor>
		<Sensor Name="340" Source="340" Enum="true"></Sensor>
		<Sensor Name="341" Source="341" Enum="true"></Sensor>
		<Sensor Name="342" Source="342" Enum="true"></Sensor>
		<Sensor Name="343" Source="343" Enum="true"></Sensor>
		<Sensor Name="344" Source="344" Enum="true"></Sensor>
		<Sensor Name="345" Source="345" Enum="true"></Sensor>
		<Sensor Name="346" Source="346" Enum="true"></Sensor>
		<Sensor Name="347" Source="347" Enum="true"></Sensor>
		<Sensor Name="348" Source="348" Enum="true"></Sensor>
		<Sensor Name="349" Source="349" Enum="true"></Sensor>
		<Sensor Name="350" Source="350" Enum="true"></Sensor>
		<Sensor Name="351" Source="351" Enum="true"></Sensor>
		<Sensor Name="352" Source="352" Enum="true"></Sensor>
		<Sensor Name="353" Source="353" Enum="true"></Sensor>
		<Sensor Name="354" Source="354" Enum="true"></Sensor>
		<Sensor Name="355" Source="355" Enum="true"></Sensor>
		<Sensor Name="356" Source="356" Enum="true"></Sensor>
		<Sensor Name="357" Source="357" Enum="true"></Sensor>
		<Sensor Name="358" Source="358" Enum="true"></Sensor>
		<Sensor Name="359" Source="359" Enum="true"></Sensor>
		<Sensor Name="360" Source="360" Enum="true"></Sensor>
		<Sensor Name="361" Source="361" Enum="true"></Sensor>
		<Sensor Name="362" Source="362" Enum="true"></Sensor>
		<Sensor Name="363" Source="363" Enum="true"></Sensor>
		<Sensor Name="364" Source="364" Enum="true"></Sensor>
		<Sensor Name="365" Source="365" Enum="true"></Sensor>
		<Sensor Name="366" Source="366" Enum="true"></Sensor>
		<Sensor Name="367" Source="367" Enum="true"></Sensor>
		<Sensor Name="368" Source="368" Enum="true"></Sensor>
		<Sensor Name="369" Source="369" Enum="true"></Sensor>
		<Sensor Name="370" Source="370" Enum="true"></Sensor>
		<Sensor Name="371" Source="371" Enum="true"></Sensor>
		<Sensor Name="372" Source="372" Enum="true"></Sensor>
		<Sensor Name="373" Source="373" Enum="true"></Sensor>
		<Sensor Name="374" Source="374" Enum="true"></Sensor>
		<Sensor Name="375" Source="375" Enum="true"></Sensor>
		<Sensor Name="376" Source="376" Enum="true"></Sensor>
		<Sensor Name="377" Source="377" Enum="true"></Sensor>
		<Sensor Name="378" Source="378" Enum="true"></Sensor>
		<Sensor Name="379" Source="379" Enum="true"></Sensor>
		<Sensor Name="380" Source="380" Enum="true"></Sensor>
		<Sensor Name="381" Source="381" Enum="true"></Sensor>
		<Sensor Name="382" Source="382" Enum="true"></Sensor>
		<Sensor Name="383" Source="383" Enum="true"></Sensor>
		<Sensor Name="384" Source="384" Enum="true"></Sensor>
		<Sensor Name="385" Source="385" Enum="true"></Sensor>
		<Sensor Name="386" Source="386" Enum="true"></Sensor>
		<Sensor Name="387" Source="387" Enum="true"></Sensor>
		<Sensor Name="388" Source="388" Enum="true"></Sensor>
		<Sensor Name="389" Source="389" Enum="true"></Sensor>
		<Sensor Name="390" Source="390" Enum="true"></Sensor>
		<Sensor Name="391" Source="391" Enum="true"></Sensor>
		<Sensor Name="392" Source="392" Enum="true"></Sensor>
		<Sensor Name="393" Source="393" Enum="true"></Sensor>
		<Sensor Name="394" Source="394" Enum="true"></Sensor>
		<Sensor Name="395" Source="395" Enum="true"></Sensor>
		<Sensor Name="396" Source="396" Enum="true"></Sensor>
		<Sensor Name="397" Source="397" Enum="true"></Sensor>
		<Sensor Name="398" Source="398" Enum="true"></Sensor>
		<Sensor Name="399" Source="399" Enum="true"></Sensor>
		<Sensor Name="400" Source="400" Enum="true"></Sensor>
		<Sensor Name="401" Source="401" Enum="true"></Sensor>
		<Sensor Name="402" Source="402" Enum="true"></Sensor>
		<Sensor Name="403" Source="403" Enum="true"></Sensor>
		<Sensor Name="404" Source="404" Enum="true"></Sensor>
		<Sensor Name="405" Source="405" Enum="true"></Sensor>
		<Sensor Name="406" Source="406" Enum="true"></Sensor>
		<Sensor Name="407" Source="407" Enum="true"></Sensor>
		<Sensor Name="408" Source="408" Enum="true"></Sensor>
		<Sensor Name="409" Source="409" Enum="true"></Sensor>
		<Sensor Name="410" Source="410" Enum="true"></Sensor>
		<Sensor Name="411" Source="411" Enum="true"></Sensor>
		<Sensor Name="412" Source="412" Enum="true"></Sensor>
		<Sensor Name="413" Source="413" Enum="true"></Sensor>
		<Sensor Name="414" Source="414" Enum="true"></Sensor>
		<Sensor Name="415" Source="415" Enum="true"></Sensor>
		<Sensor Name="416" Source="416" Enum="true"></Sensor>
		<Sensor Name="417" Source="417" Enum="true"></Sensor>
		<Sensor Name="418" Source="418" Enum="true"></Sensor>
		<Sensor Name="419" Source="419" Enum="true"></Sensor>
		<Sensor Name="420" Source="420" Enum="true"></Sensor>
		<Sensor Name="421" Source="421" Enum="true"></Sensor>
		<Sensor Name="422" Source="422" Enum="true"></Sensor>
		<Sensor Name="423" Source="423" Enum="true"></Sensor>
		<Sensor Name="424" Source="424" Enum="true"></Sensor>
		<Sensor Name="425" Source="425" Enum="true"></Sensor>
		<Sensor Name="426" Source="426" Enum="true"></Sensor>
		<Sensor Name="427" Source="427" Enum="true"></Sensor>
		<Sensor Name="428" Source="428" Enum="true"></Sensor>
		<Sensor Name="429" Source="429" Enum="true"></Sensor>
		<Sensor Name="430" Source="430" Enum="true"></Sensor>
		<Sensor Name="431" Source="431" Enum="true"></Sensor>
		<Sensor Name="432" Source="432" Enum="true"></Sensor>
		<Sensor Name="433" Source="433" Enum="true"></Sensor>
		<Sensor Name="434" Source="434" Enum="true"></Sensor>
		<Sensor Name="435" Source="435" Enum="true"></Sensor>
		<Sensor Name="436" Source="436" Enum="true"></Sensor>
		<Sensor Name="437" Source="437" Enum="true"></Sensor>
		<Sensor Name="438" Source="438" Enum="true"></Sensor>
		<Sensor Name="439" Source="439" Enum="true"></Sensor>
		<Sensor Name="440" Source="440" Enum="true"></Sensor>
		<Sensor Name="441" Source="441" Enum="true"></Sensor>
		<Sensor Name="442" Source="442" Enum="true"></Sensor>
		<Sensor Name="443" Source="443" Enum="true"></Sensor>
		<Sensor Name="444" Source="444" Enum="true"></Sensor>
		<Sensor Name="445" Source="445" Enum="true"></Sensor>
		<Sensor Name="446" Source="446" Enum="true"></Sensor>
		<Sensor Name="447" Source="447" Enum="true"></Sensor>
		<Sensor Name="448" Source="448" Enum="true"></Sensor>
		<Sensor Name="449" Source="449" Enum="true"></Sensor>
		<Sensor Name="450" Source="450" Enum="true"></Sensor>
		<Sensor Name="451" Source="451" Enum="true"></Sensor>
		<Sensor Name="452" Source="452" Enum="true"></Sensor>
		<Sensor Name="453" Source="453" Enum="true"></Sensor>
		<Sensor Name="454" Source="454" Enum="true"></Sensor>
		<Sensor Name="455" Source="455" Enum="true"></Sensor>
		<Sensor Name="456" Source="456" Enum="true"></Sensor>
		<Sensor Name="457" Source="457" Enum="true"></Sensor>
		<Sensor Name="458" Source="458" Enum="true"></Sensor>
		<Sensor Name="459" Source="459" Enum="true"></Sensor>
		<Sensor Name="460" Source="460" Enum="true"></Sensor>
		<Sensor Name="461" Source="461" Enum="true"></Sensor>
		<Sensor Name="462" Source="462" Enum="true"></Sensor>
		<Sensor Name="463" Source="463" Enum="true"></Sensor>
		<Sensor Name="464" Source="464" Enum="true"></Sensor>
		<Sensor Name="465" Source="465" Enum="true"></Sensor>
		<Sensor Name="466" Source="466" Enum="true"></Sensor>
		<Sensor Name="467" Source="467" Enum="true"></Sensor>
		<Sensor Name="468" Source="468" Enum="true"></Sensor>
		<Sensor Name="469" Source="469" Enum="true"></Sensor>
		<Sensor Name="470" Source="470" Enum="true"></Sensor>
		<Sensor Name="471" Source="471" Enum="true"></Sensor>
		<Sensor Name="472" Source="472" Enum="true"></Sensor>
		<Sensor Name="473" Source="473" Enum="true"></Sensor>
		<Sensor Name="474" Source="474" Enum="true"></Sensor>
		<Sensor Name="475" Source="475" Enum="true"></Sensor>
		<Sensor Name="476" Source="476" Enum="true"></Sensor>
		<Sensor Name="477" Source="477" Enum="true"></Sensor>
		<Sensor Name="478" Source="478" Enum="true"></Sensor>
		<Sensor Name="479" Source="479" Enum="true"></Sensor>
		<Sensor Name="480" Source="480" Enum="true"></Sensor>
		<Sensor Name="481" Source="481" Enum="true"></Sensor>
		<Sensor Name="482" Source="482" Enum="true"></Sensor>
		<Sensor Name="483" Source="483" Enum="true"></Sensor>
		<Sensor Name="484" Source="484" Enum="true"></Sensor>
		<Sensor Name="485" Source="485" Enum="true"></Sensor>
		<Sensor Name="486" Source="486" Enum="true"></Sensor>
		<Sensor Name="487" Source="487" Enum="true"></Sensor>
		<Sensor Name="488" Source="488" Enum="true"></Sensor>
		<Sensor Name="489" Source="489" Enum="true"></Sensor>
		<Sensor Name="490" Source="490" Enum="true"></Sensor>
		<Sensor Name="491" Source="491" Enum="true"></Sensor>
		<Sensor Name="492" Source="492" Enum="true"></Sensor>
		<Sensor Name="493" Source="493" Enum="true"></Sensor>
		<Sensor Name="494" Source="494" Enum="true"></Sensor>
		<Sensor Name="495" Source="495" Enum="true"></Sensor>
		<Sensor Name="496" Source="496" Enum="true"></Sensor>
		<Sensor Name="497" Source="497" Enum="true"></Sensor>
		<Sensor Name="498" Source="498" Enum="true"></Sensor>
		<Sensor Name="499" Source="499" Enum="true"></Sensor>
		<Sensor Name="500" Source="500" Enum="true"></Sensor>
		<Sensor Name="501" Source="501" Enum="true"></Sensor>
		<Sensor Name="502" Source="502" Enum="true"></Sensor>
		<Sensor Name="503" Source="503" Enum="true"></Sensor>
		<Sensor Name="504" Source="504" Enum="true"></Sensor>
		<Sensor Name="505" Source="505" Enum="true"></Sensor>
		<Sensor Name="506" Source="506" Enum="true"></Sensor>
		<Sensor Name="507" Source="507" Enum="true"></Sensor>
		<Sensor Name="508" Source="508" Enum="true"></Sensor>
		<Sensor Name="509" Source="509" Enum="true"></Sensor>
		<Sensor Name="510" Source="510" Enum="true"></Sensor>
		<Sensor Name="511" Source="511" Enum="true"></Sensor>
		<Sensor Name="512" Source="512" Enum="true"></Sensor>
		<Sensor Name="513" Source="513" Enum="true"></Sensor>
		<Sensor Name="514" Source="514" Enum="true"></Sensor>
		<Sensor Name="515" Source="515" Enum="true"></Sensor>
		<Sensor Name="516" Source="516" Enum="true"></Sensor>
		<Sensor Name="517" Source="517" Enum="true"></Sensor>
		<Sensor Name="518" Source="518" Enum="true"></Sensor>
		<Sensor Name="519" Source="519" Enum="true"></Sensor>
		<Sensor Name="520" Source="520" Enum="true"></Sensor>
		<Sensor Name="521" Source="521" Enum="true"></Sensor>
		<Sensor Name="522" Source="522" Enum="true"></Sensor>
		<Sensor Name="523" Source="523" Enum="true"></Sensor>
		<Sensor Name="524" Source="524" Enum="true"></Sensor>
		<Sensor Name="525" Source="525" Enum="true"></Sensor>
		<Sensor Name="526" Source="526" Enum="true"></Sensor>
		<Sensor Name="527" Source="527" Enum="true"></Sensor>
		<Sensor Name="528" Source="528" Enum="true"></Sensor>
		<Sensor Name="529" Source="529" Enum="true"></Sensor>
		<Sensor Name="530" Source="530" Enum="true"></Sensor>
		<Sensor Name="531" Source="531" Enum="true"></Sensor>
		<Sensor Name="532" Source="532" Enum="true"></Sensor>
		<Sensor Name="533" Source="533" Enum="true"></Sensor>
		<Sensor Name="534" Source="534" Enum="true"></Sensor>
		<Sensor Name="535" Source="535" Enum="true"></Sensor>
		<Sensor Name="536" Source="536" Enum="true"></Sensor>
		<Sensor Name="537" Source="537" Enum="true"></Sensor>
		<Sensor Name="538" Source="538" Enum="true"></Sensor>
		<Sensor Name="539" Source="539" Enum="true"></Sensor>
		<Sensor Name="540" Source="540" Enum="true"></Sensor>
		<Sensor Name="541" Source="541" Enum="true"></Sensor>
		<Sensor Name="542" Source="542" Enum="true"></Sensor>
		<Sensor Name="543" Source="543" Enum="true"></Sensor>
		<Sensor Name="544" Source="544" Enum="true"></Sensor>
		<Sensor Name="545" Source="545" Enum="true"></Sensor>
		<Sensor Name="546" Source="546" Enum="true"></Sensor>
		<Sensor Name="547" Source="547" Enum="true"></Sensor>
		<Sensor Name="548" Source="548" Enum="true"></Sensor>
		<Sensor Name="549" Source="549" Enum="true"></Sensor>
		<Sensor Name="550" Source="550" Enum="true"></Sensor>
		<Sensor Name="551" Source="551" Enum="true"></Sensor>
		<Sensor Name="552" Source="552" Enum="true"></Sensor>
		<Sensor Name="553" Source="553" Enum="true"></Sensor>
		<Sensor Name="554" Source="554" Enum="true"></Sensor>
		<Sensor Name="555" Source="555" Enum="true"></Sensor>
		<Sensor Name="556" Source="556" Enum="true"></Sensor>
		<Sensor Name="557" Source="557" Enum="true"></Sensor>
		<Sensor Name="558" Source="558" Enum="true"></Sensor>
		<Sensor Name="559" Source="559" Enum="true"></Sensor>
		<Sensor Name="560" Source="560" Enum="true"></Sensor>
		<Sensor Name="561" Source="561" Enum="true"></Sensor>
		<Sensor Name="562" Source="562" Enum="true"></Sensor>
		<Sensor Name="563" Source="563" Enum="true"></Sensor>
		<Sensor Name="564" Source="564" Enum="true"></Sensor>
		<Sensor Name="565" Source="565" Enum="true"></Sensor>
		<Sensor Name="566" Source="566" Enum="true"></Sensor>
		<Sensor Name="567" Source="567" Enum="true"></Sensor>
		<Sensor Name="568" Source="568" Enum="true"></Sensor>
		<Sensor Name="569" Source="569" Enum="true"></Sensor>
		<Sensor Name="570" Source="570" Enum="true"></Sensor>
		<Sensor Name="571" Source="571" Enum="true"></Sensor>
		<Sensor Name="572" Source="572" Enum="true"></Sensor>
		<Sensor Name="573" Source="573" Enum="true"></Sensor>
		<Sensor Name="574" Source="574" Enum="true"></Sensor>
		<Sensor Name="575" Source="575" Enum="true"></Sensor>
		<Sensor Name="576" Source="576" Enum="true"></Sensor>
		<Sensor Name="577" Source="577" Enum="true"></Sensor>
		<Sensor Name="578" Source="578" Enum="true"></Sensor>
		<Sensor Name="579" Source="579" Enum="true"></Sensor>
		<Sensor Name="580" Source="580" Enum="true"></Sensor>
		<Sensor Name="581" Source="581" Enum="true"></Sensor>
		<Sensor Name="582" Source="582" Enum="true"></Sensor>
		<Sensor Name="583" Source="583" Enum="true"></Sensor>
		<Sensor Name="584" Source="584" Enum="true"></Sensor>
		<Sensor Name="585" Source="585" Enum="true"></Sensor>
		<Sensor Name="586" Source="586" Enum="true"></Sensor>
		<Sensor Name="587" Source="587" Enum="true"></Sensor>
		<Sensor Name="588" Source="588" Enum="true"></Sensor>
		<Sensor Name="589" Source="589" Enum="true"></Sensor>
		<Sensor Name="590" Source="590" Enum="true"></Sensor>
		<Sensor Name="591" Source="591" Enum="true"></Sensor>
		<Sensor Name="592" Source="592" Enum="true"></Sensor>
		<Sensor Name="593" Source="593" Enum="true"></Sensor>
		<Sensor Name="594" Source="594" Enum="true"></Sensor>
		<Sensor Name="595" Source="595" Enum="true"></Sensor>
		<Sensor Name="596" Source="596" Enum="true"></Sensor>
		<Sensor Name="597" Source="597" Enum="true"></Sensor>
		<Sensor Name="598" Source="598" Enum="true"></Sensor>
		<Sensor Name="599" Source="599" Enum="true"></Sensor>
		<Sensor Name="600" Source="600" Enum="true"></Sensor>
		<Sensor Name="601" Source="601" Enum="true"></Sensor>
		<Sensor Name="602" Source="602" Enum="true"></Sensor>
		<Sensor Name="603" Source="603" Enum="true"></Sensor>
		<Sensor Name="604" Source="604" Enum="true"></Sensor>
		<Sensor Name="605" Source="605" Enum="true"></Sensor>
		<Sensor Name="606" Source="606" Enum="true"></Sensor>
		<Sensor Name="607" Source="607" Enum="true"></Sensor>
		<Sensor Name="608" Source="608" Enum="true"></Sensor>
		<Sensor Name="609" Source="609" Enum="true"></Sensor>
		<Sensor Name="610" Source="610" Enum="true"></Sensor>
		<Sensor Name="611" Source="611" Enum="true"></Sensor>
		<Sensor Name="612" Source="612" Enum="true"></Sensor>
		<Sensor Name="613" Source="613" Enum="true"></Sensor>
		<Sensor Name="614" Source="614" Enum="true"></Sensor>
		<Sensor Name="615" Source="615" Enum="true"></Sensor>
		<Sensor Name="616" Source="616" Enum="true"></Sensor>
		<Sensor Name="617" Source="617" Enum="true"></Sensor>
		<Sensor Name="618" Source="618" Enum="true"></Sensor>
		<Sensor Name="619" Source="619" Enum="true"></Sensor>
		<Sensor Name="620" Source="620" Enum="true"></Sensor>
		<Sensor Name="621" Source="621" Enum="true"></Sensor>
		<Sensor Name="622" Source="622" Enum="true"></Sensor>
		<Sensor Name="623" Source="623" Enum="true"></Sensor>
		<Sensor Name="624" Source="624" Enum="true"></Sensor>
		<Sensor Name="625" Source="625" Enum="true"></Sensor>
		<Sensor Name="626" Source="626" Enum="true"></Sensor>
		<Sensor Name="627" Source="627" Enum="true"></Sensor>
		<Sensor Name="628" Source="628" Enum="true"></Sensor>
		<Sensor Name="629" Source="629" Enum="true"></Sensor>
		<Sensor Name="630" Source="630" Enum="true"></Sensor>
		<Sensor Name="631" Source="631" Enum="true"></Sensor>
		<Sensor Name="632" Source="632" Enum="true"></Sensor>
		<Sensor Name="633" Source="633" Enum="true"></Sensor>
		<Sensor Name="634" Source="634" Enum="true"></Sensor>
		<Sensor Name="635" Source="635" Enum="true"></Sensor>
		<Sensor Name="636" Source="636" Enum="true"></Sensor>
		<Sensor Name="637" Source="637" Enum="true"></Sensor>
		<Sensor Name="638" Source="638" Enum="true"></Sensor>
		<Sensor Name="639" Source="639" Enum="true"></Sensor>
		<Sensor Name="640" Source="640" Enum="true"></Sensor>
		<Sensor Name="641" Source="641" Enum="true"></Sensor>
		<Sensor Name="642" Source="642" Enum="true"></Sensor>
		<Sensor Name="643" Source="643" Enum="true"></Sensor>
		<Sensor Name="644" Source="644" Enum="true"></Sensor>
		<Sensor Name="645" Source="645" Enum="true"></Sensor>
		<Sensor Name="646" Source="646" Enum="true"></Sensor>
		<Sensor Name="647" Source="647" Enum="true"></Sensor>
		<Sensor Name="648" Source="648" Enum="true"></Sensor>
		<Sensor Name="649" Source="649" Enum="true"></Sensor>
		<Sensor Name="650" Source="650" Enum="true"></Sensor>
		<Sensor Name="651" Source="651" Enum="true"></Sensor>
		<Sensor Name="652" Source="652" Enum="true"></Sensor>
		<Sensor Name="653" Source="653" Enum="true"></Sensor>
		<Sensor Name="654" Source="654" Enum="true"></Sensor>
		<Sensor Name="655" Source="655" Enum="true"></Sensor>
		<Sensor Name="656" Source="656" Enum="true"></Sensor>
		<Sensor Name="657" Source="657" Enum="true"></Sensor>
		<Sensor Name="658" Source="658" Enum="true"></Sensor>
		<Sensor Name="659" Source="659" Enum="true"></Sensor>
		<Sensor Name="660" Source="660" Enum="true"></Sensor>
		<Sensor Name="661" Source="661" Enum="true"></Sensor>
		<Sensor Name="662" Source="662" Enum="true"></Sensor>
		<Sensor Name="663" Source="663" Enum="true"></Sensor>
		<Sensor Name="664" Source="664" Enum="true"></Sensor>
		<Sensor Name="665" Source="665" Enum="true"></Sensor>
		<Sensor Name="666" Source="666" Enum="true"></Sensor>
		<Sensor Name="667" Source="667" Enum="true"></Sensor>
		<Sensor Name="668" Source="668" Enum="true"></Sensor>
		<Sensor Name="669" Source="669" Enum="true"></Sensor>
		<Sensor Name="670" Source="670" Enum="true"></Sensor>
		<Sensor Name="671" Source="671" Enum="true"></Sensor>
		<Sensor Name="672" Source="672" Enum="true"></Sensor>
		<Sensor Name="673" Source="673" Enum="true"></Sensor>
		<Sensor Name="674" Source="674" Enum="true"></Sensor>
		<Sensor Name="675" Source="675" Enum="true"></Sensor>
		<Sensor Name="676" Source="676" Enum="true"></Sensor>
		<Sensor Name="677" Source="677" Enum="true"></Sensor>
		<Sensor Name="678" Source="678" Enum="true"></Sensor>
		<Sensor Name="679" Source="679" Enum="true"></Sensor>
		<Sensor Name="680" Source="680" Enum="true"></Sensor>
		<Sensor Name="681" Source="681" Enum="true"></Sensor>
		<Sensor Name="682" Source="682" Enum="true"></Sensor>
		<Sensor Name="683" Source="683" Enum="true"></Sensor>
		<Sensor Name="684" Source="684" Enum="true"></Sensor>
		<Sensor Name="685" Source="685" Enum="true"></Sensor>
		<Sensor Name="686" Source="686" Enum="true"></Sensor>
		<Sensor Name="687" Source="687" Enum="true"></Sensor>
		<Sensor Name="688" Source="688" Enum="true"></Sensor>
		<Sensor Name="689" Source="689" Enum="true"></Sensor>
		<Sensor Name="690" Source="690" Enum="true"></Sensor>
		<Sensor Name="691" Source="691" Enum="true"></Sensor>
		<Sensor Name="692" Source="692" Enum="true"></Sensor>
		<Sensor Name="693" Source="693" Enum="true"></Sensor>
		<Sensor Name="694" Source="694" Enum="true"></Sensor>
		<Sensor Name="695" Source="695" Enum="true"></Sensor>
		<Sensor Name="696" Source="696" Enum="true"></Sensor>
		<Sensor Name="697" Source="697" Enum="true"></Sensor>
		<Sensor Name="698" Source="698" Enum="true"></Sensor>
		<Sensor Name="699" Source="699" Enum="true"></Sensor>
		<Sensor Name="700" Source="700" Enum="true"></Sensor>
		<Sensor Name="701" Source="701" Enum="true"></Sensor>
		<Sensor Name="702" Source="702" Enum="true"></Sensor>
		<Sensor Name="703" Source="703" Enum="true"></Sensor>
		<Sensor Name="704" Source="704" Enum="true"></Sensor>
		<Sensor Name="705" Source="705" Enum="true"></Sensor>
		<Sensor Name="706" Source="706" Enum="true"></Sensor>
		<Sensor Name="707" Source="707" Enum="true"></Sensor>
		<Sensor Name="708" Source="708" Enum="true"></Sensor>
		<Sensor Name="709" Source="709" Enum="true"></Sensor>
		<Sensor Name="710" Source="710" Enum="true"></Sensor>
		<Sensor Name="711" Source="711" Enum="true"></Sensor>
		<Sensor Name="712" Source="712" Enum="true"></Sensor>
		<Sensor Name="713" Source="713" Enum="true"></Sensor>
		<Sensor Name="714" Source="714" Enum="true"></Sensor>
		<Sensor Name="715" Source="715" Enum="true"></Sensor>
		<Sensor Name="716" Source="716" Enum="true"></Sensor>
		<Sensor Name="717" Source="717" Enum="true"></Sensor>
		<Sensor Name="718" Source="718" Enum="true"></Sensor>
		<Sensor Name="719" Source="719" Enum="true"></Sensor>
		<Sensor Name="720" Source="720" Enum="true"></Sensor>
		<Sensor Name="721" Source="721" Enum="true"></Sensor>
		<Sensor Name="722" Source="722" Enum="true"></Sensor>
		<Sensor Name="723" Source="723" Enum="true"></Sensor>
		<Sensor Name="724" Source="724" Enum="true"></Sensor>
		<Sensor Name="725" Source="725" Enum="true"></Sensor>
		<Sensor Name="726" Source="726" Enum="true"></Sensor>
		<Sensor Name="727" Source="727" Enum="true"></Sensor>
		<Sensor Name="728" Source="728" Enum="true"></Sensor>
		<Sensor Name="729" Source="729" Enum="true"></Sensor>
		<Sensor Name="730" Source="730" Enum="true"></Sensor>
		<Sensor Name="731" Source="731" Enum="true"></Sensor>
		<Sensor Name="732" Source="732" Enum="true"></Sensor>
		<Sensor Name="733" Source="733" Enum="true"></Sensor>
		<Sensor Name="734" Source="734" Enum="true"></Sensor>
		<Sensor Name="735" Source="735" Enum="true"></Sensor>
		<Sensor Name="736" Source="736" Enum="true"></Sensor>
		<Sensor Name="737" Source="737" Enum="true"></Sensor>
		<Sensor Name="738" Source="738" Enum="true"></Sensor>
		<Sensor Name="739" Source="739" Enum="true"></Sensor>
		<Sensor Name="740" Source="740" Enum="true"></Sensor>
		<Sensor Name="741" Source="741" Enum="true"></Sensor>
		<Sensor Name="742" Source="742" Enum="true"></Sensor>
		<Sensor Name="743" Source="743" Enum="true"></Sensor>
		<Sensor Name="744" Source="744" Enum="true"></Sensor>
		<Sensor Name="745" Source="745" Enum="true"></Sensor>
		<Sensor Name="746" Source="746" Enum="true"></Sensor>
		<Sensor Name="747" Source="747" Enum="true"></Sensor>
		<Sensor Name="748" Source="748" Enum="true"></Sensor>
		<Sensor Name="749" Source="749" Enum="true"></Sensor>
		<Sensor Name="750" Source="750" Enum="true"></Sensor>
		<Sensor Name="751" Source="751" Enum="true"></Sensor>
		<Sensor Name="752" Source="752" Enum="true"></Sensor>
		<Sensor Name="753" Source="753" Enum="true"></Sensor>
		<Sensor Name="754" Source="754" Enum="true"></Sensor>
		<Sensor Name="755" Source="755" Enum="true"></Sensor>
		<Sensor Name="756" Source="756" Enum="true"></Sensor>
		<Sensor Name="757" Source="757" Enum="true"></Sensor>
		<Sensor Name="758" Source="758" Enum="true"></Sensor>
		<Sensor Name="759" Source="759" Enum="true"></Sensor>
		<Sensor Name="760" Source="760" Enum="true"></Sensor>
		<Sensor Name="761" Source="761" Enum="true"></Sensor>
		<Sensor Name="762" Source="762" Enum="true"></Sensor>
		<Sensor Name="763" Source="763" Enum="true"></Sensor>
		<Sensor Name="764" Source="764" Enum="true"></Sensor>
		<Sensor Name="765" Source="765" Enum="true"></Sensor>
		<Sensor Name="766" Source="766" Enum="true"></Sensor>
		<Sensor Name="767" Source="767" Enum="true"></Sensor>
		<Sensor Name="768" Source="768" Enum="true"></Sensor>
		<Sensor Name="769" Source="769" Enum="true"></Sensor>
		<Sensor Name="770" Source="770" Enum="true"></Sensor>
		<Sensor Name="771" Source="771" Enum="true"></Sensor>
		<Sensor Name="772" Source="772" Enum="true"></Sensor>
		<Sensor Name="773" Source="773" Enum="true"></Sensor>
		<Sensor Name="774" Source="774" Enum="true"></Sensor>
		<Sensor Name="775" Source="775" Enum="true"></Sensor>
		<Sensor Name="776" Source="776" Enum="true"></Sensor>
		<Sensor Name="777" Source="777" Enum="true"></Sensor>
		<Sensor Name="778" Source="778" Enum="true"></Sensor>
		<Sensor Name="779" Source="779" Enum="true"></Sensor>
		<Sensor Name="780" Source="780" Enum="true"></Sensor>
		<Sensor Name="781" Source="781" Enum="true"></Sensor>
		<Sensor Name="782" Source="782" Enum="true"></Sensor>
		<Sensor Name="783" Source="783" Enum="true"></Sensor>
		<Sensor Name="784" Source="784" Enum="true"></Sensor>

	
	  	<Controller Name="Controller" Oracle="test">
              <ErrorMargin ErrorAllowed="2000.0" AugmentationFactorError="5.0" DiminutionFactorError="0.4" MinErrorAllowed="0.1" NConflictBeforeAugmentation="40" NSuccessBeforeDiminution="80" />
              
        </Controller> 


			
	</StartingAgents>
	
	
</System>
